gpuci/__init__.py
gpuci/__main__.py
gpuci/cli.py
gpuci/config.py
gpuci/exceptions.py
gpuci/reporter.py
gpuci/runner.py
gpuci/timing.py
gpuci/providers/__init__.py
gpuci/providers/base.py
gpuci/providers/brev.py
gpuci/providers/fluidstack.py
gpuci/providers/lambdalabs.py
gpuci/providers/runpod.py
gpuci/providers/ssh.py
gpuci/providers/vastai.py
gpuci-0.1.1.dist-info/licenses/LICENSE
gpuci-0.1.1.dist-info/METADATA
gpuci-0.1.1.dist-info/WHEEL
gpuci-0.1.1.dist-info/entry_points.txt
gpuci-0.1.1.dist-info/top_level.txt
gpuci-0.1.1.dist-info/RECORD
