Metadata-Version: 2.4
Name: gpuci
Version: 0.1.1
Summary: Test CUDA kernels across multiple GPUs via SSH
Author-email: RightNow AI <hello@rightnow.ai>
License-Expression: PolyForm-Noncommercial-1.0.0
Project-URL: Homepage, https://www.rightnowai.co/
Project-URL: Documentation, https://github.com/rightnow-ai/gpuci#readme
Project-URL: Repository, https://github.com/rightnow-ai/gpuci
Project-URL: Issues, https://github.com/rightnow-ai/gpuci/issues
Project-URL: Changelog, https://github.com/rightnow-ai/gpuci/blob/main/CHANGELOG.md
Keywords: gpu,cuda,testing,ssh,nvidia,benchmark,ci,ml,deep-learning
Classifier: Development Status :: 4 - Beta
Classifier: Environment :: Console
Classifier: Intended Audience :: Developers
Classifier: Intended Audience :: Science/Research
Classifier: Operating System :: OS Independent
Classifier: Programming Language :: Python :: 3
Classifier: Programming Language :: Python :: 3.9
Classifier: Programming Language :: Python :: 3.10
Classifier: Programming Language :: Python :: 3.11
Classifier: Programming Language :: Python :: 3.12
Classifier: Topic :: Software Development :: Testing
Classifier: Topic :: System :: Hardware :: Symmetric Multi-processing
Requires-Python: >=3.9
License-File: LICENSE
Requires-Dist: click>=8.0
Requires-Dist: paramiko>=3.0
Requires-Dist: pyyaml>=6.0
Requires-Dist: rich>=13.0
Requires-Dist: httpx>=0.24.0
Provides-Extra: runpod
Requires-Dist: runpod>=1.0; extra == "runpod"
Provides-Extra: vastai
Requires-Dist: vastai-sdk>=0.1.0; extra == "vastai"
Provides-Extra: cloud
Requires-Dist: gpuci[runpod]; extra == "cloud"
Requires-Dist: gpuci[vastai]; extra == "cloud"
Dynamic: license-file
